native/wpimath/_init_robotpy_native_wpimath.py
native/wpimath/robotpy-native-wpimath.pc
native/wpimath/include/.clang-format
native/wpimath/include/.styleguide
native/wpimath/include/gcem.hpp
native/wpimath/include/Eigen/Cholesky
native/wpimath/include/Eigen/Core
native/wpimath/include/Eigen/Eigenvalues
native/wpimath/include/Eigen/Geometry
native/wpimath/include/Eigen/Householder
native/wpimath/include/Eigen/IterativeLinearSolvers
native/wpimath/include/Eigen/Jacobi
native/wpimath/include/Eigen/LU
native/wpimath/include/Eigen/OrderingMethods
native/wpimath/include/Eigen/QR
native/wpimath/include/Eigen/SVD
native/wpimath/include/Eigen/SparseCholesky
native/wpimath/include/Eigen/SparseCore
native/wpimath/include/Eigen/SparseLU
native/wpimath/include/Eigen/SparseQR
native/wpimath/include/Eigen/src/Cholesky/InternalHeaderCheck.h
native/wpimath/include/Eigen/src/Cholesky/LDLT.h
native/wpimath/include/Eigen/src/Cholesky/LLT.h
native/wpimath/include/Eigen/src/Core/ArithmeticSequence.h
native/wpimath/include/Eigen/src/Core/Array.h
native/wpimath/include/Eigen/src/Core/ArrayBase.h
native/wpimath/include/Eigen/src/Core/ArrayWrapper.h
native/wpimath/include/Eigen/src/Core/Assign.h
native/wpimath/include/Eigen/src/Core/AssignEvaluator.h
native/wpimath/include/Eigen/src/Core/BandMatrix.h
native/wpimath/include/Eigen/src/Core/Block.h
native/wpimath/include/Eigen/src/Core/CommaInitializer.h
native/wpimath/include/Eigen/src/Core/ConditionEstimator.h
native/wpimath/include/Eigen/src/Core/CoreEvaluators.h
native/wpimath/include/Eigen/src/Core/CoreIterators.h
native/wpimath/include/Eigen/src/Core/CwiseBinaryOp.h
native/wpimath/include/Eigen/src/Core/CwiseNullaryOp.h
native/wpimath/include/Eigen/src/Core/CwiseTernaryOp.h
native/wpimath/include/Eigen/src/Core/CwiseUnaryOp.h
native/wpimath/include/Eigen/src/Core/CwiseUnaryView.h
native/wpimath/include/Eigen/src/Core/DenseBase.h
native/wpimath/include/Eigen/src/Core/DenseCoeffsBase.h
native/wpimath/include/Eigen/src/Core/DenseStorage.h
robotpy_native_wpimath-2025.3.2.dist-info/METADATA
robotpy_native_wpimath-2025.3.2.dist-info/WHEEL
robotpy_native_wpimath-2025.3.2.dist-info/entry_points.txt
robotpy_native_wpimath-2025.3.2.dist-info/RECORD
