Metadata-Version: 2.4
Name: robotpy-native-wpimath
Version: 2025.3.2
Summary: WPILib Math Library
License-Expression: BSD-3-Clause
Requires-Dist: robotpy-native-wpiutil==2025.3.2
